Metadata-Version: 2.4
Name: agent-control-engine
Version: 0.0.1
Summary: Coming soon...
Project-URL: Homepage, https://github.com/rungalileo/agent-control
Author: Lev
License-Expression: MIT
License-File: LICENSE
Classifier: Development Status :: 1 - Planning
Classifier: Programming Language :: Python :: 3
Requires-Python: >=3.9
